<?xml version="1.0" encoding="UTF-8"?>
<!DOCTYPE mapper PUBLIC "-//mybatis.org//DTD Mapper 3.0//EN" "http://mybatis.org/dtd/mybatis-3-mapper.dtd">
<mapper namespace="com.scale.invest.indicator.provider.dao.InvestStockMainDao">
    <resultMap id="BaseResultMap" type="com.scale.invest.api.model.InvestStockMain">
        <id column="id" jdbcType="BIGINT" property="id" />
        <result column="stock_code" jdbcType="VARCHAR" property="stockCode" />
        <result column="stock_name" jdbcType="VARCHAR" property="stockName" />
        <result column="create_time" jdbcType="TIMESTAMP" property="createTime" />
        <result column="update_time" jdbcType="TIMESTAMP" property="updateTime" />
    </resultMap>
    <sql id="BaseTable">
        invest_stock_main
    </sql>
</mapper>
